LICENSE
MANIFEST.in
README.md
setup.py
cascade_trainer/__init__.py
cascade_trainer/train.py
cascade_trainer.egg-info/PKG-INFO
cascade_trainer.egg-info/SOURCES.txt
cascade_trainer.egg-info/dependency_links.txt
cascade_trainer.egg-info/entry_points.txt
cascade_trainer.egg-info/not-zip-safe
cascade_trainer.egg-info/requires.txt
cascade_trainer.egg-info/top_level.txt
cascade_trainer/data/opencv_createsamples.exe
cascade_trainer/data/opencv_traincascade.exe
cascade_trainer/data/opencv_world320.dll
cascade_trainer/data/tbb.dll