Metadata-Version: 2.1
Name: cascade-trainer
Version: 2022.2.8
Summary: An OpenCV based cascade trainer
Home-page: https://github.com/egeakman/cascade-trainer
Download-URL: https://github.com/egeakman/cascade-trainer/archive/2022.2.8.tar.gz
Author: Ege Akman
Author-email: egeakmanegeakman@hotmail.com
License: AGPLv3
Project-URL: Homepage, https://github.com/egeakman/cascade-trainer
Project-URL: Issues, https://github.com/egeakman/cascade-trainer/issues
Keywords: OpenCV,Cascade,Trainer,CLI,HaarObject Detection,Video Processing,Computer Vision
Platform: UNKNOWN
Classifier: Topic :: Utilities
Classifier: Topic :: Scientific/Engineering :: Image Recognition
Classifier: Topic :: Scientific/Engineering
Classifier: Topic :: Software Development
Classifier: Programming Language :: Python :: 3 :: Only
Classifier: Development Status :: 5 - Production/Stable
Classifier: Intended Audience :: Developers
Classifier: Intended Audience :: Science/Research
Classifier: Environment :: Console
Classifier: License :: OSI Approved :: GNU Affero General Public License v3 or later (AGPLv3+)
Classifier: Operating System :: Microsoft :: Windows
Requires-Python: >=3.6
License-File: LICENSE
